{
  "_class": "shapePath",
  "booleanOperation": -1,
  "clippingMaskMode": 0,
  "do_objectID": "C3D81335-F995-47A3-B395-CBEFFD4E8164",
  "edited": true,
  "exportOptions": {
    "_class": "exportOptions",
    "exportFormats": [
    ],
    "includedLayerIds": [
    ],
    "layerOptions": 0,
    "shouldTrim": false
  },
  "frame": {
    "_class": "rect",
    "constrainProportions": false,
    "height": 4,
    "width": 3,
    "x": 32,
    "y": 112
  },
  "hasClippingMask": false,
  "isClosed": false,
  "isFixedToViewport": false,
  "isFlippedHorizontal": false,
  "isFlippedVertical": false,
  "isLocked": false,
  "isVisible": true,
  "layerListExpandedType": 0,
  "name": "Fill 955",
  "nameIsFixed": false,
  "pointRadiusBehaviour": 1,
  "points": [
    {
      "_class": "curvePoint",
      "cornerRadius": 0,
      "curveFrom": "{0.94263616514001547, 0.56949017521773382}",
      "curveMode": 4,
      "curveTo": "{0.99890543354434347, 0.91118762114591845}",
      "hasCurveFrom": true,
      "hasCurveTo": false,
      "point": "{0.99890543354434347, 0.91118762114591845}"
    },
    {
      "_class": "curvePoint",
      "cornerRadius": 0,
      "curveFrom": "{-0.0005387640896203674, -0.017112372092439994}",
      "curveMode": 3,
      "curveTo": "{0.68371471745921697, 0.062881838136742349}",
      "hasCurveFrom": true,
      "hasCurveTo": true,
      "point": "{0.15713286910376276, 0.0013265857893879078}"
    },
    {
      "_class": "curvePoint",
      "cornerRadius": 0,
      "curveFrom": "{0.49812637906600893, 0.22867000129449999}",
      "curveMode": 3,
      "curveTo": "{-0.068249305116827669, 0.16245221069861318}",
      "hasCurveFrom": true,
      "hasCurveTo": true,
      "point": "{0.090664523389895682, 0.18103738058126639}"
    },
    {
      "_class": "curvePoint",
      "cornerRadius": 0,
      "curveFrom": "{0.76829296326758112, 1.0289045275879676}",
      "curveMode": 3,
      "curveTo": "{0.70528968869093089, 0.64646267076319752}",
      "hasCurveFrom": true,
      "hasCurveTo": true,
      "point": "{0.74889728205927308, 0.91118762114591845}"
    },
    {
      "_class": "curvePoint",
      "cornerRadius": 0,
      "curveFrom": "{0.99890543354434347, 0.91118762114591845}",
      "curveMode": 4,
      "curveTo": "{1.0185190437549918, 1.0303016644847407}",
      "hasCurveFrom": false,
      "hasCurveTo": true,
      "point": "{0.99890543354434347, 0.91118762114591845}"
    }
  ],
  "resizingConstraint": 63,
  "resizingType": 0,
  "rotation": 0,
  "shouldBreakMaskChain": false,
  "style": {
    "_class": "style",
    "endMarkerType": 0,
    "fills": [
      {
        "_class": "fill",
        "color": {
          "_class": "color",
          "alpha": 1,
          "blue": 0.302,
          "green": 0.161,
          "red": 0.757
        },
        "fillType": 0,
        "isEnabled": true,
        "noiseIndex": 0,
        "noiseIntensity": 0,
        "patternFillType": 1,
        "patternTileScale": 1
      }
    ],
    "miterLimit": 10,
    "startMarkerType": 0,
    "windingRule": 1
  }
}