{
  "_class": "shapePath",
  "booleanOperation": -1,
  "clippingMaskMode": 0,
  "do_objectID": "938A3CBC-8598-4821-8F32-53D2C5D0CD87",
  "edited": true,
  "exportOptions": {
    "_class": "exportOptions",
    "exportFormats": [
    ],
    "includedLayerIds": [
    ],
    "layerOptions": 0,
    "shouldTrim": false
  },
  "frame": {
    "_class": "rect",
    "constrainProportions": false,
    "height": 41.79159628378379,
    "width": 26.82643581081081,
    "x": 20.18757057752329,
    "y": 3.547297297297298
  },
  "hasClippingMask": false,
  "isClosed": true,
  "isFixedToViewport": false,
  "isFlippedHorizontal": false,
  "isFlippedVertical": false,
  "isLocked": false,
  "isVisible": true,
  "layerListExpandedType": 0,
  "name": "Path",
  "nameIsFixed": false,
  "pointRadiusBehaviour": 1,
  "points": [
    {
      "_class": "curvePoint",
      "cornerRadius": 0,
      "curveFrom": "{0.77135123966942154, 0}",
      "curveMode": 4,
      "curveTo": "{0.49586776859504111, 0}",
      "hasCurveFrom": true,
      "hasCurveTo": false,
      "point": "{0.49586776859504111, 0}"
    },
    {
      "_class": "curvePoint",
      "cornerRadius": 0,
      "curveFrom": "{0.91597797520661151, 0.0022104376657824318}",
      "curveMode": 2,
      "curveTo": "{0.91046830578512428, 0.00044208222811676734}",
      "hasCurveFrom": true,
      "hasCurveTo": true,
      "point": "{0.91322314049586761, 0.0013262599469496847}"
    },
    {
      "_class": "curvePoint",
      "cornerRadius": 0,
      "curveFrom": "{0.86225884297520672, 0.044208753315649996}",
      "curveMode": 4,
      "curveTo": "{0.90633619834710777, 0.010609999999999991}",
      "hasCurveFrom": true,
      "hasCurveTo": true,
      "point": "{0.88429752066115719, 0.026525198938992162}"
    },
    {
      "_class": "curvePoint",
      "cornerRadius": 0,
      "curveFrom": "{0.73553719008264451, 0.15119363395225469}",
      "curveMode": 4,
      "curveTo": "{0.81267256198347115, 0.085764482758620683}",
      "hasCurveFrom": false,
      "hasCurveTo": true,
      "point": "{0.73553719008264451, 0.15119363395225469}"
    },
    {
      "_class": "curvePoint",
      "cornerRadius": 0,
      "curveFrom": "{0.61570247933884281, 0.25198938992042447}",
      "curveMode": 1,
      "curveTo": "{0.61570247933884281, 0.25198938992042447}",
      "hasCurveFrom": false,
      "hasCurveTo": false,
      "point": "{0.61570247933884281, 0.25198938992042447}"
    },
    {
      "_class": "curvePoint",
      "cornerRadius": 0,
      "curveFrom": "{0.61570247933884281, 0.44297082228116713}",
      "curveMode": 1,
      "curveTo": "{0.61570247933884281, 0.44297082228116713}",
      "hasCurveFrom": false,
      "hasCurveTo": false,
      "point": "{0.61570247933884281, 0.44297082228116713}"
    },
    {
      "_class": "curvePoint",
      "cornerRadius": 0,
      "curveFrom": "{1, 0.44297082228116713}",
      "curveMode": 1,
      "curveTo": "{1, 0.44297082228116713}",
      "hasCurveFrom": false,
      "hasCurveTo": false,
      "point": "{1, 0.44297082228116713}"
    },
    {
      "_class": "curvePoint",
      "cornerRadius": 0,
      "curveFrom": "{1, 0.49336870026525198}",
      "curveMode": 1,
      "curveTo": "{1, 0.49336870026525198}",
      "hasCurveFrom": false,
      "hasCurveTo": false,
      "point": "{1, 0.49336870026525198}"
    },
    {
      "_class": "curvePoint",
      "cornerRadius": 0,
      "curveFrom": "{0.61570247933884281, 0.49336870026525198}",
      "curveMode": 1,
      "curveTo": "{0.61570247933884281, 0.49336870026525198}",
      "hasCurveFrom": false,
      "hasCurveTo": false,
      "point": "{0.61570247933884281, 0.49336870026525198}"
    },
    {
      "_class": "curvePoint",
      "cornerRadius": 0,
      "curveFrom": "{0.61570247933884281, 0.87002652519893886}",
      "curveMode": 1,
      "curveTo": "{0.61570247933884281, 0.87002652519893886}",
      "hasCurveFrom": false,
      "hasCurveTo": false,
      "point": "{0.61570247933884281, 0.87002652519893886}"
    },
    {
      "_class": "curvePoint",
      "cornerRadius": 0,
      "curveFrom": "{0.59504128099173548, 0.89832013262599475}",
      "curveMode": 4,
      "curveTo": "{0.60330578512396704, 0.88594164456233426}",
      "hasCurveFrom": true,
      "hasCurveTo": false,
      "point": "{0.60330578512396704, 0.88594164456233426}"
    },
    {
      "_class": "curvePoint",
      "cornerRadius": 0,
      "curveFrom": "{0.54683185950413216, 0.93457124668434999}",
      "curveMode": 4,
      "curveTo": "{0.58264471074380153, 0.90981427055702901}",
      "hasCurveFrom": true,
      "hasCurveTo": true,
      "point": "{0.56611570247933884, 0.92042440318302388}"
    },
    {
      "_class": "curvePoint",
      "cornerRadius": 0,
      "curveFrom": "{0.49586768595041358, 0.95844389920424389}",
      "curveMode": 4,
      "curveTo": "{0.52892570247933912, 0.94429705570291766}",
      "hasCurveFrom": true,
      "hasCurveTo": true,
      "point": "{0.5123966942148761, 0.9496021220159151}"
    },
    {
      "_class": "curvePoint",
      "cornerRadius": 0,
      "curveFrom": "{0.4146004132231404, 0.98054822281167098}",
      "curveMode": 4,
      "curveTo": "{0.47245194214876035, 0.96640137931034464}",
      "hasCurveFrom": true,
      "hasCurveTo": true,
      "point": "{0.44214876033057871, 0.97347480106100781}"
    },
    {
      "_class": "curvePoint",
      "cornerRadius": 0,
      "curveFrom": "{0.30027528925619806, 0.99734750663129978}",
      "curveMode": 2,
      "curveTo": "{0.3801654958677686, 0.98673737400530503}",
      "hasCurveFrom": true,
      "hasCurveTo": true,
      "point": "{0.33884297520661139, 0.99204244031830224}"
    },
    {
      "_class": "curvePoint",
      "cornerRadius": 0,
      "curveFrom": "{0.24931123966942165, 1}",
      "curveMode": 2,
      "curveTo": "{0.27410475206611579, 1}",
      "hasCurveFrom": true,
      "hasCurveTo": true,
      "point": "{0.26033057851239666, 1}"
    },
    {
      "_class": "curvePoint",
      "cornerRadius": 0,
      "curveFrom": "{0.24380165289256209, 0.99115824933686991}",
      "curveMode": 2,
      "curveTo": "{0.24380165289256209, 0.99823167108753308}",
      "hasCurveFrom": true,
      "hasCurveTo": true,
      "point": "{0.24380165289256209, 0.99469496021220161}"
    },
    {
      "_class": "curvePoint",
      "cornerRadius": 0,
      "curveFrom": "{0.30578524793388417, 0.96728554376657816}",
      "curveMode": 2,
      "curveTo": "{0.25619822314049595, 0.98496909814323608}",
      "hasCurveFrom": true,
      "hasCurveTo": true,
      "point": "{0.28099173553718998, 0.97612732095490706}"
    },
    {
      "_class": "curvePoint",
      "cornerRadius": 0,
      "curveFrom": "{0.37327834710743818, 0.9319185941644561}",
      "curveMode": 2,
      "curveTo": "{0.32920099173553713, 0.95667557029177719}",
      "hasCurveFrom": true,
      "hasCurveTo": true,
      "point": "{0.35123966942148765, 0.94429708222811659}"
    },
    {
      "_class": "curvePoint",
      "cornerRadius": 0,
      "curveFrom": "{0.4077135537190083, 0.8965516710875332}",
      "curveMode": 4,
      "curveTo": "{0.38842971074380167, 0.91954029177718832}",
      "hasCurveFrom": true,
      "hasCurveTo": true,
      "point": "{0.39669421487603301, 0.90716180371352784}"
    },
    {
      "_class": "curvePoint",
      "cornerRadius": 0,
      "curveFrom": "{0.42699727272727256, 0.86030055702917763}",
      "curveMode": 2,
      "curveTo": "{0.41597793388429755, 0.8850575331564986}",
      "hasCurveFrom": true,
      "hasCurveTo": true,
      "point": "{0.42148760330578505, 0.87267904509283811}"
    },
    {
      "_class": "curvePoint",
      "cornerRadius": 0,
      "curveFrom": "{0.42975206611570238, 0.67374005305039797}",
      "curveMode": 4,
      "curveTo": "{0.42975206611570238, 0.79398822281167103}",
      "hasCurveFrom": false,
      "hasCurveTo": true,
      "point": "{0.42975206611570238, 0.67374005305039797}"
    },
    {
      "_class": "curvePoint",
      "cornerRadius": 0,
      "curveFrom": "{0.42975206611570238, 0.49336870026525198}",
      "curveMode": 1,
      "curveTo": "{0.42975206611570238, 0.49336870026525198}",
      "hasCurveFrom": false,
      "hasCurveTo": false,
      "point": "{0.42975206611570238, 0.49336870026525198}"
    },
    {
      "_class": "curvePoint",
      "cornerRadius": 0,
      "curveFrom": "{0, 0.49336870026525198}",
      "curveMode": 1,
      "curveTo": "{0, 0.49336870026525198}",
      "hasCurveFrom": false,
      "hasCurveTo": false,
      "point": "{0, 0.49336870026525198}"
    },
    {
      "_class": "curvePoint",
      "cornerRadius": 0,
      "curveFrom": "{0, 0.44297082228116713}",
      "curveMode": 1,
      "curveTo": "{0, 0.44297082228116713}",
      "hasCurveFrom": false,
      "hasCurveTo": false,
      "point": "{0, 0.44297082228116713}"
    },
    {
      "_class": "curvePoint",
      "cornerRadius": 0,
      "curveFrom": "{0.42975206611570238, 0.44297082228116713}",
      "curveMode": 1,
      "curveTo": "{0.42975206611570238, 0.44297082228116713}",
      "hasCurveFrom": false,
      "hasCurveTo": false,
      "point": "{0.42975206611570238, 0.44297082228116713}"
    },
    {
      "_class": "curvePoint",
      "cornerRadius": 0,
      "curveFrom": "{0.42975206611570238, 0.25198938992042447}",
      "curveMode": 1,
      "curveTo": "{0.42975206611570238, 0.25198938992042447}",
      "hasCurveFrom": false,
      "hasCurveTo": false,
      "point": "{0.42975206611570238, 0.25198938992042447}"
    },
    {
      "_class": "curvePoint",
      "cornerRadius": 0,
      "curveFrom": "{0.54958677685950408, 0.15119363395225469}",
      "curveMode": 1,
      "curveTo": "{0.54958677685950408, 0.15119363395225469}",
      "hasCurveFrom": false,
      "hasCurveTo": false,
      "point": "{0.54958677685950408, 0.15119363395225469}"
    },
    {
      "_class": "curvePoint",
      "cornerRadius": 0,
      "curveFrom": "{0.67355371900826477, 0.053050397877984157}",
      "curveMode": 1,
      "curveTo": "{0.67355371900826477, 0.053050397877984157}",
      "hasCurveFrom": false,
      "hasCurveTo": false,
      "point": "{0.67355371900826477, 0.053050397877984157}"
    },
    {
      "_class": "curvePoint",
      "cornerRadius": 0,
      "curveFrom": "{0.37603305785123969, 0.050397877984084953}",
      "curveMode": 1,
      "curveTo": "{0.37603305785123969, 0.050397877984084953}",
      "hasCurveFrom": false,
      "hasCurveTo": false,
      "point": "{0.37603305785123969, 0.050397877984084953}"
    },
    {
      "_class": "curvePoint",
      "cornerRadius": 0,
      "curveFrom": "{0.078512396694214878, 0.050397877984084953}",
      "curveMode": 1,
      "curveTo": "{0.078512396694214878, 0.050397877984084953}",
      "hasCurveFrom": false,
      "hasCurveTo": false,
      "point": "{0.078512396694214878, 0.050397877984084953}"
    },
    {
      "_class": "curvePoint",
      "cornerRadius": 0,
      "curveFrom": "{0.078512396694214878, 0}",
      "curveMode": 1,
      "curveTo": "{0.078512396694214878, 0}",
      "hasCurveFrom": false,
      "hasCurveTo": false,
      "point": "{0.078512396694214878, 0}"
    }
  ],
  "resizingConstraint": 63,
  "resizingType": 0,
  "rotation": 0,
  "shouldBreakMaskChain": false,
  "style": {
    "_class": "style",
    "endMarkerType": 0,
    "miterLimit": 10,
    "startMarkerType": 0,
    "windingRule": 1
  }
}