{
  "_class": "shapeGroup",
  "booleanOperation": 0,
  "clippingMaskMode": 0,
  "do_objectID": "C9CEA3EF-6384-41F4-881F-A9A0640052B6",
  "exportOptions": {
    "_class": "exportOptions",
    "do_objectID": "BB6BB0B3-026B-4671-B734-7FD5E3E0A546",
    "exportFormats": [
    ],
    "includedLayerIds": [
    ],
    "layerOptions": 0,
    "shouldTrim": false
  },
  "frame": {
    "_class": "rect",
    "constrainProportions": false,
    "do_objectID": "6D6361F6-2B25-4875-A8E7-DBCA6792C49C",
    "height": 2.768652037617553,
    "width": 2.768652037617557,
    "x": 41.52978056426333,
    "y": 16.61191222570533
  },
  "groupLayout": {
    "_class": "MSImmutableFreeformGroupLayout",
    "do_objectID": "7A4253B8-CBF2-4503-ACEB-EDBA30B161EF"
  },
  "hasClickThrough": false,
  "hasClippingMask": false,
  "isFixedToViewport": false,
  "isFlippedHorizontal": false,
  "isFlippedVertical": false,
  "isLocked": false,
  "isVisible": true,
  "layerListExpandedType": 0,
  "layers": [
    {
      "class": "rectangle",
      "id": "CCF3B8B9-08E8-40AF-9571-5EBC00533FD7"
    }
  ],
  "name": "Shape",
  "nameIsFixed": false,
  "resizingConstraint": 63,
  "resizingType": 0,
  "rotation": 0,
  "shouldBreakMaskChain": false,
  "style": {
    "_class": "style",
    "blur": {
      "_class": "blur",
      "center": "{0.5, 0.5}",
      "do_objectID": "2770894A-49E1-4D6F-B953-74C5B86727CF",
      "isEnabled": false,
      "motionAngle": 0,
      "radius": 3.15,
      "saturation": 1,
      "type": 0
    },
    "do_objectID": "1179F813-5BBD-4C8C-A4B6-ACD9463CBE3A",
    "endMarkerType": 0,
    "fills": [
      {
        "_class": "fill",
        "color": {
          "_class": "color",
          "alpha": 1,
          "blue": 0,
          "green": 0,
          "red": 0
        },
        "fillType": 0,
        "isEnabled": true,
        "noiseIndex": 0,
        "noiseIntensity": 0,
        "patternFillType": 1,
        "patternTileScale": 1
      }
    ],
    "miterLimit": 10,
    "startMarkerType": 0,
    "windingRule": 1
  },
  "windingRule": 1
}