{
  "_class": "shapePath",
  "booleanOperation": -1,
  "clippingMaskMode": 0,
  "do_objectID": "8CDB2042-619C-423D-8440-FF8C6BC64430",
  "edited": true,
  "exportOptions": {
    "_class": "exportOptions",
    "do_objectID": "489B1D72-1A8B-4D86-9C62-6E5F9312332A",
    "exportFormats": [
    ],
    "includedLayerIds": [
    ],
    "layerOptions": 0,
    "shouldTrim": false
  },
  "frame": {
    "_class": "rect",
    "constrainProportions": false,
    "do_objectID": "729BD17D-7855-4D42-8329-AD3B5EAD4B2E",
    "height": 0.2303833624508805,
    "width": 0.5101187601775174,
    "x": 0.1032718981385973,
    "y": 11.37225961538465
  },
  "hasClippingMask": false,
  "isClosed": false,
  "isFixedToViewport": false,
  "isFlippedHorizontal": false,
  "isFlippedVertical": false,
  "isLocked": false,
  "isVisible": true,
  "layerListExpandedType": 0,
  "name": "Path",
  "nameIsFixed": false,
  "pointRadiusBehaviour": 1,
  "points": [
    {
      "_class": "curvePoint",
      "cornerRadius": 0,
      "curveFrom": "{0.052125826551082229, 1.0498805010347596}",
      "curveMode": 4,
      "curveTo": "{0.00039672664871489915, 0.99281007379902708}",
      "hasCurveFrom": true,
      "hasCurveTo": false,
      "point": "{0.00039672664871489915, 0.99281007379902708}"
    },
    {
      "_class": "curvePoint",
      "cornerRadius": 0,
      "curveFrom": "{1, 0.18520968838767671}",
      "curveMode": 4,
      "curveTo": "{0.37678751070016547, 0.76596409887459271}",
      "hasCurveFrom": false,
      "hasCurveTo": true,
      "point": "{1, 0.18520968838767671}"
    },
    {
      "_class": "curvePoint",
      "cornerRadius": 0,
      "curveFrom": "{0.98062211495722196, 0.12885712816118178}",
      "curveMode": 4,
      "curveTo": "{1, 0.18520968838767671}",
      "hasCurveFrom": true,
      "hasCurveTo": false,
      "point": "{1, 0.18520968838767671}"
    },
    {
      "_class": "curvePoint",
      "cornerRadius": 0,
      "curveFrom": "{0.92856457632532363, 0}",
      "curveMode": 4,
      "curveTo": "{0.94827090009765136, 0.05635256022647453}",
      "hasCurveFrom": false,
      "hasCurveTo": true,
      "point": "{0.92856457632532363, 0}"
    },
    {
      "_class": "curvePoint",
      "cornerRadius": 0,
      "curveFrom": "{0.29254297657346201, 0.65218217790774646}",
      "curveMode": 4,
      "curveTo": "{0.92856457632532363, 0}",
      "hasCurveFrom": true,
      "hasCurveTo": false,
      "point": "{0.92856457632532363, 0}"
    },
    {
      "_class": "curvePoint",
      "cornerRadius": 0,
      "curveFrom": "{0.00039672664871489915, 0.99281007379902708}",
      "curveMode": 4,
      "curveTo": "{-0.012576603168058975, 0.99281007379902708}",
      "hasCurveFrom": false,
      "hasCurveTo": true,
      "point": "{0.00039672664871489915, 0.99281007379902708}"
    }
  ],
  "resizingConstraint": 63,
  "resizingType": 0,
  "rotation": 0,
  "shouldBreakMaskChain": false,
  "style": {
    "_class": "style",
    "blur": {
      "_class": "blur",
      "center": "{0.5, 0.5}",
      "do_objectID": "C4562E42-A3A0-4CBF-A7FE-4264463EEFFF",
      "isEnabled": false,
      "motionAngle": 0,
      "radius": 3,
      "saturation": 1,
      "type": 0
    },
    "do_objectID": "6390A173-8CC5-491C-A5AB-9C9DB87F422A",
    "endMarkerType": 0,
    "miterLimit": 10,
    "startMarkerType": 0,
    "windingRule": 1
  }
}