{
  "_class": "shapePath",
  "booleanOperation": -1,
  "clippingMaskMode": 0,
  "do_objectID": "B1669882-C8B6-4EBD-AE6F-1B073020A824",
  "edited": true,
  "exportOptions": {
    "_class": "exportOptions",
    "exportFormats": [
    ],
    "includedLayerIds": [
    ],
    "layerOptions": 0,
    "shouldTrim": false
  },
  "frame": {
    "_class": "rect",
    "constrainProportions": false,
    "height": 7.651120645928524,
    "width": 11.99231790875605,
    "x": 4.112460716322737,
    "y": 3.940450926976615
  },
  "hasClippingMask": false,
  "isClosed": false,
  "isFixedToViewport": false,
  "isFlippedHorizontal": false,
  "isFlippedVertical": false,
  "isLocked": false,
  "isVisible": true,
  "layerListExpandedType": 0,
  "name": "Path",
  "nameIsFixed": false,
  "pointRadiusBehaviour": 1,
  "points": [
    {
      "_class": "curvePoint",
      "cornerRadius": 0,
      "curveFrom": "{0.85686968201759361, 0.89181707871661509}",
      "curveMode": 4,
      "curveTo": "{0.92529246150635047, 0.77580731089171984}",
      "hasCurveFrom": true,
      "hasCurveTo": false,
      "point": "{0.92529246150635047, 0.77580731089171984}"
    },
    {
      "_class": "curvePoint",
      "cornerRadius": 0,
      "curveFrom": "{0.55126393896301629, 1.0113516814328405}",
      "curveMode": 3,
      "curveTo": "{0.75501177121842533, 0.95277746551894305}",
      "hasCurveFrom": true,
      "hasCurveTo": true,
      "point": "{0.65795012387035789, 0.9806747335899989}"
    },
    {
      "_class": "curvePoint",
      "cornerRadius": 0,
      "curveFrom": "{0.24729607452855917, 0.93300155099798465}",
      "curveMode": 3,
      "curveTo": "{0.44028832600819129, 1.0048964612399285}",
      "hasCurveFrom": true,
      "hasCurveTo": true,
      "point": "{0.33491457804075025, 0.96564604325760262}"
    },
    {
      "_class": "curvePoint",
      "cornerRadius": 0,
      "curveFrom": "{0.03914144181640887, 0.65155060157523093}",
      "curveMode": 2,
      "curveTo": "{0.15383029099144194, 0.87074342213352707}",
      "hasCurveFrom": true,
      "hasCurveTo": true,
      "point": "{0.095320144975598403, 0.75892829155460984}"
    },
    {
      "_class": "curvePoint",
      "cornerRadius": 0,
      "curveFrom": "{0.013458224626632657, 0.24271998935744532}",
      "curveMode": 3,
      "curveTo": "{-0.0114567367934446, 0.50271214584318946}",
      "hasCurveFrom": true,
      "hasCurveTo": true,
      "point": "{0.0022758350899126393, 0.35943304965472056}"
    },
    {
      "_class": "curvePoint",
      "cornerRadius": 0,
      "curveFrom": "{0.20995564305551359, 0.036529707008737956}",
      "curveMode": 3,
      "curveTo": "{0.070367837788938264, 0.15931285114500271}",
      "hasCurveFrom": true,
      "hasCurveTo": true,
      "point": "{0.13310339053812273, 0.10414625471037309}"
    },
    {
      "_class": "curvePoint",
      "cornerRadius": 0,
      "curveFrom": "{0.4787598006977371, -0.0060194875702263857}",
      "curveMode": 2,
      "curveTo": "{0.30103663264085895, 0.0092938687628948378}",
      "hasCurveFrom": true,
      "hasCurveTo": true,
      "point": "{0.3881109549828472, 0.0017920823908465359}"
    },
    {
      "_class": "curvePoint",
      "cornerRadius": 0,
      "curveFrom": "{0.76187805716010304, 0.12392216923133047}",
      "curveMode": 3,
      "curveTo": "{0.57265239299579807, 0.011286530767970733}",
      "hasCurveFrom": true,
      "hasCurveTo": true,
      "point": "{0.65781141102305207, 0.061982196485331292}"
    },
    {
      "_class": "curvePoint",
      "cornerRadius": 0,
      "curveFrom": "{0.95011139095521591, 0.43990980256558149}",
      "curveMode": 3,
      "curveTo": "{0.84957658731497154, 0.25608254633265704}",
      "hasCurveFrom": true,
      "hasCurveTo": true,
      "point": "{0.92096568769228604, 0.38661028019453059}"
    },
    {
      "_class": "curvePoint",
      "cornerRadius": 0,
      "curveFrom": "{0.98696632746268764, 0.64293526878858132}",
      "curveMode": 4,
      "curveTo": "{0.97830744472504583, 0.49933801648165405}",
      "hasCurveFrom": true,
      "hasCurveTo": true,
      "point": "{1, 0.56340461170365908}"
    },
    {
      "_class": "curvePoint",
      "cornerRadius": 0,
      "curveFrom": "{0.92529246150635047, 0.77580731089171984}",
      "curveMode": 4,
      "curveTo": "{0.95943182727231902, 0.71793638745020139}",
      "hasCurveFrom": false,
      "hasCurveTo": true,
      "point": "{0.92529246150635047, 0.77580731089171984}"
    }
  ],
  "resizingConstraint": 63,
  "resizingType": 0,
  "rotation": 0,
  "shouldBreakMaskChain": false,
  "style": {
    "_class": "style",
    "endMarkerType": 0,
    "miterLimit": 10,
    "startMarkerType": 0,
    "windingRule": 1
  }
}