{
  "_class": "bitmap",
  "booleanOperation": 0,
  "clippingMask": "{{0, 0}, {1, 1}}",
  "clippingMaskMode": 0,
  "do_objectID": "88FE1852-B33F-4B12-A5CA-3E28D816B331",
  "exportOptions": {
    "_class": "exportOptions",
    "do_objectID": "7F63E3C0-E1EE-4B66-B5E8-B609B2140710",
    "exportFormats": [
    ],
    "includedLayerIds": [
    ],
    "layerOptions": 0,
    "shouldTrim": false
  },
  "fillReplacesImage": false,
  "frame": {
    "_class": "rect",
    "constrainProportions": true,
    "do_objectID": "CFE4D507-B1B6-41F6-B200-8ACD37FE2CC1",
    "height": 306,
    "width": 446,
    "x": 0,
    "y": 0
  },
  "hasClippingMask": false,
  "image": {
    "_class": "MSJSONFileReference",
    "_ref": "images/6128e84fab0c8bb92478686110d75628706ae705.png",
    "_ref_class": "MSImageData"
  },
  "intendedDPI": 0,
  "isFixedToViewport": false,
  "isFlippedHorizontal": false,
  "isFlippedVertical": false,
  "isLocked": false,
  "isVisible": true,
  "layerListExpandedType": 0,
  "name": "Shadow",
  "nameIsFixed": false,
  "resizingConstraint": 63,
  "resizingType": 0,
  "rotation": 0,
  "shouldBreakMaskChain": false,
  "style": {
    "_class": "style",
    "blur": {
      "_class": "blur",
      "center": "{0.5, 0.5}",
      "do_objectID": "D043C780-1A0F-4D07-AF11-65579D3A61BB",
      "isEnabled": false,
      "motionAngle": 0,
      "radius": 1.5,
      "saturation": 1,
      "type": 0
    },
    "contextSettings": {
      "_class": "graphicsContextSettings",
      "blendMode": 2,
      "do_objectID": "EC6D061A-0E2F-499B-8B62-49114553C308",
      "opacity": 1
    },
    "do_objectID": "B64AC516-BE07-4483-B2AF-420411400411",
    "endMarkerType": 0,
    "miterLimit": 10,
    "startMarkerType": 0,
    "windingRule": 1
  }
}