{
  "_class": "group",
  "booleanOperation": -1,
  "clippingMaskMode": 0,
  "do_objectID": "16CD5184-265A-4B3B-B855-33565BC956CD",
  "exportOptions": {
    "_class": "exportOptions",
    "do_objectID": "16C8BB8E-C43B-42F6-B089-D063D94BF3B9",
    "exportFormats": [
    ],
    "includedLayerIds": [
    ],
    "layerOptions": 0,
    "shouldTrim": false
  },
  "frame": {
    "_class": "rect",
    "constrainProportions": false,
    "do_objectID": "9A024B2B-4962-4067-A229-4A57DFCD108D",
    "height": 46,
    "width": 179,
    "x": 93,
    "y": 567
  },
  "groupLayout": {
    "_class": "MSImmutableFreeformGroupLayout",
    "do_objectID": "9776BC56-EF85-4F08-8C8B-A555726C9EDE"
  },
  "hasClickThrough": false,
  "hasClippingMask": false,
  "isFixedToViewport": false,
  "isFlippedHorizontal": false,
  "isFlippedVertical": false,
  "isLocked": false,
  "isVisible": true,
  "layerListExpandedType": 0,
  "layers": [
    {
      "class": "symbolInstance",
      "id": "DA6039BC-295A-4607-BF73-E6A0402BBEE7"
    },
    {
      "class": "symbolInstance",
      "id": "4C8C41AA-4C85-4F64-A436-32A45C441355"
    },
    {
      "class": "symbolInstance",
      "id": "AA876804-C7D2-4CA7-BE0B-652C5144CE62"
    }
  ],
  "name": "Group",
  "nameIsFixed": false,
  "resizingConstraint": 63,
  "resizingType": 0,
  "rotation": 0,
  "shouldBreakMaskChain": false,
  "style": {
    "_class": "style",
    "do_objectID": "F62A0EFD-323A-42FA-9C2A-CB0A48CE34C2",
    "endMarkerType": 0,
    "miterLimit": 10,
    "startMarkerType": 0,
    "windingRule": 1
  }
}