{
  "_class": "group",
  "booleanOperation": -1,
  "clippingMaskMode": 0,
  "do_objectID": "74005ABD-3AE3-4321-839D-DD2BC0F51D17",
  "exportOptions": {
    "_class": "exportOptions",
    "do_objectID": "4787FDF3-4758-4C31-B91D-A65BB64EBC76",
    "exportFormats": [
    ],
    "includedLayerIds": [
    ],
    "layerOptions": 0,
    "shouldTrim": false
  },
  "frame": {
    "_class": "rect",
    "constrainProportions": false,
    "do_objectID": "FAD10D44-1BAD-43DF-A161-1B59990368FC",
    "height": 177,
    "width": 110,
    "x": 0,
    "y": 0
  },
  "hasClickThrough": false,
  "hasClippingMask": false,
  "isFixedToViewport": false,
  "isFlippedHorizontal": false,
  "isFlippedVertical": false,
  "isLocked": false,
  "isVisible": true,
  "layerListExpandedType": 0,
  "layers": [
    {
      "class": "group",
      "id": "DDC4A802-46E1-40C5-96F1-A5B34EA5244C"
    },
    {
      "class": "group",
      "id": "99D9C02B-7E9C-4BFE-B567-9A8E63A0F19C"
    },
    {
      "class": "group",
      "id": "A8470E36-3DE2-41F2-8C17-A50444D3E068"
    },
    {
      "class": "oval",
      "id": "7EEE42F0-FB00-477D-AE97-5C81D3A49DA0"
    },
    {
      "class": "oval",
      "id": "8984F601-B3A9-4726-A7C3-4716F0E7550A"
    },
    {
      "class": "group",
      "id": "608456E5-4250-4CF8-B296-220486D146B2"
    },
    {
      "class": "shapePath",
      "id": "31333C0D-38FA-4F57-9BB8-79F1A7AA7E12"
    },
    {
      "class": "shapePath",
      "id": "F148AC35-3B54-48F7-BEAF-49B2081548AD"
    }
  ],
  "name": "Group 5",
  "nameIsFixed": false,
  "resizingConstraint": 63,
  "resizingType": 0,
  "rotation": 0,
  "shouldBreakMaskChain": false,
  "style": {
    "_class": "style",
    "blur": {
      "_class": "blur",
      "center": "{0.5, 0.5}",
      "do_objectID": "292F1293-C7F8-4FE3-9BF9-A4410F2DA6A8",
      "isEnabled": false,
      "motionAngle": 0,
      "radius": 11,
      "saturation": 1,
      "type": 0
    },
    "do_objectID": "ECAAD323-E7E8-4D7F-83E4-07647E06E92F",
    "endMarkerType": 0,
    "miterLimit": 10,
    "shadows": [
      {
        "_class": "shadow",
        "blurRadius": 0,
        "color": {
          "_class": "color",
          "alpha": 1,
          "blue": 0,
          "green": 0,
          "red": 0
        },
        "contextSettings": {
          "_class": "graphicsContextSettings",
          "blendMode": 0,
          "opacity": 1
        },
        "isEnabled": false,
        "offsetX": 0,
        "offsetY": 0,
        "spread": 0
      }
    ],
    "startMarkerType": 0,
    "windingRule": 1
  }
}