{
  "_class": "symbolInstance",
  "booleanOperation": -1,
  "clippingMaskMode": 0,
  "do_objectID": "C38C43BE-B3F9-45AA-850D-9C1DBC11D0F8",
  "exportOptions": {
    "_class": "exportOptions",
    "do_objectID": "E15FB81A-0B84-4ACE-B8E4-CE6D7C21A6FA",
    "exportFormats": [
    ],
    "includedLayerIds": [
    ],
    "layerOptions": 0,
    "shouldTrim": false
  },
  "frame": {
    "_class": "rect",
    "constrainProportions": false,
    "do_objectID": "8A1EFC99-E9DA-4BDC-A872-DEA60CB42029",
    "height": 44,
    "width": 148,
    "x": 160,
    "y": 0
  },
  "hasClippingMask": false,
  "horizontalSpacing": 0,
  "isFixedToViewport": false,
  "isFlippedHorizontal": false,
  "isFlippedVertical": false,
  "isLocked": false,
  "isVisible": true,
  "layerListExpandedType": 0,
  "name": "button_primary",
  "nameIsFixed": false,
  "overrideValues": [
    {
      "_class": "overrideValue",
      "do_objectID": "DFF61859-14B3-4DF8-B33E-93D1B491939E",
      "overrideName": "05C20158-70AE-4716-A9A2-6A993D8A456F_stringValue",
      "value": "分享我的作品"
    }
  ],
  "resizingConstraint": 63,
  "resizingType": 0,
  "rotation": 0,
  "scale": 1,
  "shouldBreakMaskChain": false,
  "style": {
    "_class": "style",
    "do_objectID": "40F95A33-B87F-47F9-85BF-958BF021217D",
    "endMarkerType": 0,
    "miterLimit": 10,
    "startMarkerType": 0,
    "windingRule": 1
  },
  "symbolID": "4C73362D-100A-40AC-851F-6D0685CE6388",
  "verticalSpacing": 0
}