{
  "_class": "shapePath",
  "booleanOperation": -1,
  "clippingMaskMode": 0,
  "do_objectID": "EF47AF9E-53D0-4E5E-AA5B-C028764647A6",
  "edited": true,
  "exportOptions": {
    "_class": "exportOptions",
    "exportFormats": [
    ],
    "includedLayerIds": [
    ],
    "layerOptions": 0,
    "shouldTrim": false
  },
  "frame": {
    "_class": "rect",
    "constrainProportions": false,
    "height": 53.89433981668289,
    "width": 20.0610052162562,
    "x": 23.85084162800424,
    "y": 0.08909665893156124
  },
  "hasClippingMask": false,
  "isClosed": false,
  "isFixedToViewport": false,
  "isFlippedHorizontal": false,
  "isFlippedVertical": false,
  "isLocked": false,
  "isVisible": true,
  "layerListExpandedType": 0,
  "name": "Fill 226",
  "nameIsFixed": false,
  "pointRadiusBehaviour": 1,
  "points": [
    {
      "_class": "curvePoint",
      "cornerRadius": 0,
      "curveFrom": "{0.023515673533289604, 1.000440076181941}",
      "curveMode": 4,
      "curveTo": "{0.047224645308352825, 0.99999762796517899}",
      "hasCurveFrom": true,
      "hasCurveTo": false,
      "point": "{0.047224645308352825, 0.99999762796517899}"
    },
    {
      "_class": "curvePoint",
      "cornerRadius": 0,
      "curveFrom": "{0.0070304738209956748, 0.73986894498938405}",
      "curveMode": 2,
      "curveTo": "{-0.0054430914548734008, 0.93895778066550095}",
      "hasCurveFrom": true,
      "hasCurveTo": true,
      "point": "{0.00088213109568065966, 0.83937349104046688}"
    },
    {
      "_class": "curvePoint",
      "cornerRadius": 0,
      "curveFrom": "{0.22290168773593255, 0.38057526924513746}",
      "curveMode": 4,
      "curveTo": "{0.049396729562290395, 0.60245276045784879}",
      "hasCurveFrom": true,
      "hasCurveTo": true,
      "point": "{0.16351959280662637, 0.45500689222192481}"
    },
    {
      "_class": "curvePoint",
      "cornerRadius": 0,
      "curveFrom": "{0.4847758065990827, 0.19677919315419434}",
      "curveMode": 2,
      "curveTo": "{0.30595030328224476, 0.31303503448175324}",
      "hasCurveFrom": true,
      "hasCurveTo": true,
      "point": "{0.39531706618610163, 0.25494055467156607}"
    },
    {
      "_class": "curvePoint",
      "cornerRadius": 0,
      "curveFrom": "{0.75494912686245608, 0.07040363505488198}",
      "curveMode": 2,
      "curveTo": "{0.58041119050941681, 0.14791181656217667}",
      "hasCurveFrom": true,
      "hasCurveTo": true,
      "point": "{0.66763416993137414, 0.10916415674191249}"
    },
    {
      "_class": "curvePoint",
      "cornerRadius": 0,
      "curveFrom": "{0.95146968789622399, 0.0052942931103351319}",
      "curveMode": 2,
      "curveTo": "{0.83392950642826658, 0.041713955045892551}",
      "hasCurveFrom": true,
      "hasCurveTo": true,
      "point": "{0.89266775879370241, 0.023506696451467194}"
    },
    {
      "_class": "curvePoint",
      "cornerRadius": 0,
      "curveFrom": "{1.0065146895106654, 0.0037894546986740035}",
      "curveMode": 2,
      "curveTo": "{0.99010024172846656, -0.0024434059362924893}",
      "hasCurveFrom": true,
      "hasCurveTo": true,
      "point": "{0.99828624004053734, 0.00067173819451415376}"
    },
    {
      "_class": "curvePoint",
      "cornerRadius": 0,
      "curveFrom": "{0.90031604243704544, 0.062449856646579753}",
      "curveMode": 2,
      "curveTo": "{0.98465941830410852, 0.017083480188359042}",
      "hasCurveFrom": true,
      "hasCurveTo": true,
      "point": "{0.94246296719504352, 0.039766668417469397}"
    },
    {
      "_class": "curvePoint",
      "cornerRadius": 0,
      "curveFrom": "{0.69411661736618813, 0.17584779117865879}",
      "curveMode": 2,
      "curveTo": "{0.8377784114254716, 0.09453249710852854}",
      "hasCurveFrom": true,
      "hasCurveTo": true,
      "point": "{0.76590860083427714, 0.13519914745033004}"
    },
    {
      "_class": "curvePoint",
      "cornerRadius": 0,
      "curveFrom": "{0.45791837393476165, 0.33855555051951752}",
      "curveMode": 2,
      "curveTo": "{0.61295000316042114, 0.2251138856404328}",
      "hasCurveFrom": true,
      "hasCurveTo": true,
      "point": "{0.53541296296856256, 0.28185272469344808}"
    },
    {
      "_class": "curvePoint",
      "cornerRadius": 0,
      "curveFrom": "{0.31436978296363099, 0.48965161654372769}",
      "curveMode": 4,
      "curveTo": "{0.38420901316107953, 0.40280571976407298}",
      "hasCurveFrom": true,
      "hasCurveTo": true,
      "point": "{0.32865459764994931, 0.47243986643701658}"
    },
    {
      "_class": "curvePoint",
      "cornerRadius": 0,
      "curveFrom": "{0.27686418481990971, 0.54221806601774347}",
      "curveMode": 4,
      "curveTo": "{0.3027098648838627, 0.50761449966959271}",
      "hasCurveFrom": true,
      "hasCurveTo": true,
      "point": "{0.28999574304566839, 0.52490599335025512}"
    },
    {
      "_class": "curvePoint",
      "cornerRadius": 0,
      "curveFrom": "{0.24369567999105382, 0.59331826268039689}",
      "curveMode": 4,
      "curveTo": "{0.26672543323719844, 0.55954042817864491}",
      "hasCurveFrom": true,
      "hasCurveTo": true,
      "point": "{0.25536974845684129, 0.57644092110961065}"
    },
    {
      "_class": "curvePoint",
      "cornerRadius": 0,
      "curveFrom": "{0.2223285971021578, 0.63055593934229326}",
      "curveMode": 3,
      "curveTo": "{0.23483753834307428, 0.610115860677232}",
      "hasCurveFrom": true,
      "hasCurveTo": true,
      "point": "{0.22479076426948724, 0.62646329333724504}"
    },
    {
      "_class": "curvePoint",
      "cornerRadius": 0,
      "curveFrom": "{0.2150694490743407, 0.64272583767660052}",
      "curveMode": 2,
      "curveTo": "{0.21988765551385656, 0.63462800636051531}",
      "hasCurveFrom": true,
      "hasCurveTo": true,
      "point": "{0.21746086431157452, 0.63867434964520464}"
    },
    {
      "_class": "curvePoint",
      "cornerRadius": 0,
      "curveFrom": "{0.20652261591878204, 0.65884690148152625}",
      "curveMode": 2,
      "curveTo": "{0.21307424464564217, 0.64678247045470294}",
      "hasCurveFrom": true,
      "hasCurveTo": true,
      "point": "{0.21086678442665718, 0.65080309000585967}"
    },
    {
      "_class": "curvePoint",
      "cornerRadius": 0,
      "curveFrom": "{0.16458794695107123, 0.7375512365980903}",
      "curveMode": 3,
      "curveTo": "{0.20222089856896452, 0.66680067988982861}",
      "hasCurveFrom": true,
      "hasCurveTo": true,
      "point": "{0.19797578276322381, 0.67465413573735344}"
    },
    {
      "_class": "curvePoint",
      "cornerRadius": 0,
      "curveFrom": "{0.085211356576725003, 0.93929218920142565}",
      "curveMode": 3,
      "curveTo": "{0.14051106513951031, 0.79470422776098149}",
      "hasCurveFrom": true,
      "hasCurveTo": true,
      "point": "{0.12209433773560409, 0.84288478066767669}"
    },
    {
      "_class": "curvePoint",
      "cornerRadius": 0,
      "curveFrom": "{0.047224645308352825, 0.99999762796517899}",
      "curveMode": 4,
      "curveTo": "{0.070940692276425452, 0.99965292993584121}",
      "hasCurveFrom": false,
      "hasCurveTo": true,
      "point": "{0.047224645308352825, 0.99999762796517899}"
    }
  ],
  "resizingConstraint": 63,
  "resizingType": 0,
  "rotation": 0,
  "shouldBreakMaskChain": false,
  "style": {
    "_class": "style",
    "endMarkerType": 0,
    "fills": [
      {
        "_class": "fill",
        "color": {
          "_class": "color",
          "alpha": 1,
          "blue": 0.165,
          "green": 0.055,
          "red": 0.475
        },
        "fillType": 0,
        "isEnabled": true,
        "noiseIndex": 0,
        "noiseIntensity": 0,
        "patternFillType": 1,
        "patternTileScale": 1
      }
    ],
    "miterLimit": 10,
    "startMarkerType": 0,
    "windingRule": 1
  }
}