{
  "_class": "group",
  "booleanOperation": -1,
  "clippingMaskMode": 0,
  "do_objectID": "4FB2B27C-1A77-499E-902A-B988564424E9",
  "exportOptions": {
    "_class": "exportOptions",
    "exportFormats": [
      {
        "_class": "exportFormat",
        "absoluteSize": 0,
        "fileFormat": "pdf",
        "name": "",
        "namingScheme": 0,
        "scale": 1,
        "visibleScaleType": 0
      }
    ],
    "includedLayerIds": [
    ],
    "layerOptions": 0,
    "shouldTrim": false
  },
  "frame": {
    "_class": "rect",
    "constrainProportions": false,
    "height": 580,
    "width": 661,
    "x": 271,
    "y": 124
  },
  "groupLayout": {
    "_class": "MSImmutableFreeformGroupLayout"
  },
  "hasClickThrough": false,
  "hasClippingMask": false,
  "isFixedToViewport": false,
  "isFlippedHorizontal": false,
  "isFlippedVertical": false,
  "isLocked": false,
  "isVisible": true,
  "layerListExpandedType": 2,
  "layers": [
    {
      "class": "oval",
      "id": "71DDF0DD-C685-4268-8297-5B325ACE2929"
    },
    {
      "class": "oval",
      "id": "2350ED63-8339-4CF2-969A-E398927F4CED"
    },
    {
      "class": "group",
      "id": "486557C5-124F-49A8-A4C4-F47B41E3B618"
    },
    {
      "class": "group",
      "id": "FF5D5622-FA0F-4CB1-A0D9-002E211351CE"
    },
    {
      "class": "group",
      "id": "8F902382-E55B-40A2-9288-6BA0573D34E6"
    },
    {
      "class": "group",
      "id": "85F6E5EF-C31E-4F60-87CD-C8FC5C9F9053"
    }
  ],
  "name": "Group 10",
  "nameIsFixed": false,
  "resizingConstraint": 63,
  "resizingType": 0,
  "rotation": 0,
  "shouldBreakMaskChain": false,
  "style": {
    "_class": "style",
    "endMarkerType": 0,
    "miterLimit": 10,
    "startMarkerType": 0,
    "windingRule": 1
  }
}